autoscriber/__init__.py
autoscriber/summarize.py
autoscriber-1.0.4.dist-info/LICENSE
autoscriber-1.0.4.dist-info/METADATA
autoscriber-1.0.4.dist-info/WHEEL
autoscriber-1.0.4.dist-info/top_level.txt
autoscriber-1.0.4.dist-info/RECORD
